moneyline/__init__.py
moneyline/ml_arb.py
moneyline-0.6.0.dist-info/LICENSE
moneyline-0.6.0.dist-info/METADATA
moneyline-0.6.0.dist-info/WHEEL
moneyline-0.6.0.dist-info/top_level.txt
moneyline-0.6.0.dist-info/RECORD
