Metadata-Version: 2.1
Name: moneyline
Version: 0.6.0
Summary: Python package meant to ease the use of the LiveOdds API to find arbitrage opportunities
Author: spogtrop
Author-email: spogtrop@gmail.com
Classifier: Programming Language :: Python :: 3
Classifier: License :: OSI Approved :: MIT License
Classifier: Operating System :: OS Independent
Requires-Python: >=3.6
License-File: LICENSE
